zyntra/__init__.py
zyntra/core.py
zyntra/utils/__init__.py
zyntra/utils/color.py
zyntra_py-0.1.0.dist-info/licenses/LICENSE
zyntra_py-0.1.0.dist-info/METADATA
zyntra_py-0.1.0.dist-info/WHEEL
zyntra_py-0.1.0.dist-info/top_level.txt
zyntra_py-0.1.0.dist-info/RECORD
