Metadata-Version: 2.4
Name: zyntra.py
Version: 0.1.0
Summary: Bot library for Zyntra
Author-email: Demiomad <demiomad@proton.com>
License-Expression: MIT
Requires-Python: >=3.9
License-File: LICENSE
Requires-Dist: aiohttp>=3.12.13
Requires-Dist: python-socketio[asyncio-client,client]>=5.13.0
Dynamic: license-file
